Metadata-Version: 1.0
Name: dict-str
Version: 0.0.1
Summary: a str to dict_str tool
Home-page: https://github.com/xuehongbo/work
Author: HongBo Xue
Author-email: 505386086@qq.com
License: MIT License
Keywords: str to dict_str
Platform: any
